ledgerlinker/__init__.py
ledgerlinker/client.py
ledgerlinker/test_ledgerlink.py
ledgerlinker_client-1.0.0.dist-info/METADATA
ledgerlinker_client-1.0.0.dist-info/WHEEL
ledgerlinker_client-1.0.0.dist-info/entry_points.txt
ledgerlinker_client-1.0.0.dist-info/top_level.txt
ledgerlinker_client-1.0.0.dist-info/RECORD
